<?xml version="1.0" encoding="UTF-8"?>
<xsd:schema xmlns:xsd="http://www.w3.org/2001/XMLSchema" xmlns:od="urn:schemas-microsoft-com:officedata">
<xsd:element name="dataroot">
<xsd:complexType>
<xsd:sequence>
<xsd:element ref="DefPro" minOccurs="0" maxOccurs="unbounded"/>
</xsd:sequence>
<xsd:attribute name="generated" type="xsd:dateTime"/>
</xsd:complexType>
</xsd:element>
<xsd:element name="DefPro">
<xsd:annotation>
<xsd:appinfo>
<od:index index-name="DefID" index-key="DefID " primary="no" unique="yes" clustered="no" order="asc"/>
<od:index index-name="PrimaryKey" index-key="DefID " primary="yes" unique="yes" clustered="no" order="asc"/>
<od:index index-name="RecID" index-key="RecID " primary="no" unique="no" clustered="no" order="asc"/>
</xsd:appinfo>
</xsd:annotation>
<xsd:complexType>
<xsd:sequence>
<xsd:element name="DefID" minOccurs="1" od:jetType="autonumber" od:sqlSType="int" od:autoUnique="yes" od:nonNullable="yes" type="xsd:int"/>
<xsd:element name="RecID" minOccurs="0" od:jetType="longinteger" od:sqlSType="int" type="xsd:int"/>
<xsd:element name="DftPromo" minOccurs="1" od:jetType="yesno" od:sqlSType="bit" od:nonNullable="yes" type="xsd:boolean"/>
<xsd:element name="DftD" minOccurs="0" od:jetType="text" od:sqlSType="nvarchar">
<xsd:simpleType>
<xsd:restriction base="xsd:string">
<xsd:maxLength value="1"/>
</xsd:restriction>
</xsd:simpleType>
</xsd:element>
<xsd:element name="DivPrc" minOccurs="1" od:jetType="yesno" od:sqlSType="bit" od:nonNullable="yes" type="xsd:boolean"/>
<xsd:element name="ProCd" minOccurs="0" od:jetType="text" od:sqlSType="nvarchar">
<xsd:simpleType>
<xsd:restriction base="xsd:string">
<xsd:maxLength value="15"/>
</xsd:restriction>
</xsd:simpleType>
</xsd:element>
<xsd:element name="DftPg" minOccurs="0" od:jetType="text" od:sqlSType="nvarchar">
<xsd:simpleType>
<xsd:restriction base="xsd:string">
<xsd:maxLength value="15"/>
</xsd:restriction>
</xsd:simpleType>
</xsd:element>
<xsd:element name="PgOpt" minOccurs="0" od:jetType="text" od:sqlSType="nvarchar">
<xsd:simpleType>
<xsd:restriction base="xsd:string">
<xsd:maxLength value="30"/>
</xsd:restriction>
</xsd:simpleType>
</xsd:element>
<xsd:element name="DftFlier" minOccurs="0" od:jetType="text" od:sqlSType="nvarchar">
<xsd:simpleType>
<xsd:restriction base="xsd:string">
<xsd:maxLength value="50"/>
</xsd:restriction>
</xsd:simpleType>
</xsd:element>
<xsd:element name="FlyerTyp" minOccurs="0" od:jetType="text" od:sqlSType="nvarchar">
<xsd:simpleType>
<xsd:restriction base="xsd:string">
<xsd:maxLength value="25"/>
</xsd:restriction>
</xsd:simpleType>
</xsd:element>
<xsd:element name="DftMsg" minOccurs="0" od:jetType="text" od:sqlSType="nvarchar">
<xsd:simpleType>
<xsd:restriction base="xsd:string">
<xsd:maxLength value="80"/>
</xsd:restriction>
</xsd:simpleType>
</xsd:element>
<xsd:element name="Comment" minOccurs="0" od:jetType="text" od:sqlSType="nvarchar">
<xsd:simpleType>
<xsd:restriction base="xsd:string">
<xsd:maxLength value="75"/>
</xsd:restriction>
</xsd:simpleType>
</xsd:element>
<xsd:element name="DftEff" minOccurs="0" od:jetType="datetime" od:sqlSType="datetime" type="xsd:dateTime"/>
<xsd:element name="DftExp" minOccurs="0" od:jetType="datetime" od:sqlSType="datetime" type="xsd:dateTime"/>
<xsd:element name="InFly" minOccurs="0" od:jetType="text" od:sqlSType="nvarchar">
<xsd:simpleType>
<xsd:restriction base="xsd:string">
<xsd:maxLength value="3"/>
</xsd:restriction>
</xsd:simpleType>
</xsd:element>
<xsd:element name="DtRange" minOccurs="0" od:jetType="text" od:sqlSType="nvarchar">
<xsd:simpleType>
<xsd:restriction base="xsd:string">
<xsd:maxLength value="40"/>
</xsd:restriction>
</xsd:simpleType>
</xsd:element>
<xsd:element name="FreeItem" minOccurs="1" od:jetType="yesno" od:sqlSType="bit" od:nonNullable="yes" type="xsd:boolean"/>
<xsd:element name="Notes" minOccurs="0" od:jetType="text" od:sqlSType="nvarchar">
<xsd:simpleType>
<xsd:restriction base="xsd:string">
<xsd:maxLength value="250"/>
</xsd:restriction>
</xsd:simpleType>
</xsd:element>
</xsd:sequence>
</xsd:complexType>
</xsd:element>
</xsd:schema>
